Workbook

Sheet SalesData
A1: Order_ID | B1: Order_Date | C1: Employee_ID | D1: Product | E1: Units_Sold | F1: Unit_Price | G1: Payment_Method | H1: Total_Sales | I1: Discount | J1: Profit
A2: 1001 | B2: 2026-08-01 | C2: 101 | D2: Laptop | E2: 1 | F2: 65000 | G2: Online | H2: 65000 | I2: 5000 | J2: 60000
A3: 1002 | B3: 2026-08-02 | C3: 104 | D3: Mouse | E3: 5 | F3: 800 | G3: Card | H3: 4000 | I3: 200 | J3: 3800
A4: 1003 | B4: 2026-08-03 | C4: 105 | D4: Keyboard | E4: 3 | F4: 1500 | G4: UPI | H4: 4500 | I4: 300 | J4: 4200
A5: 1004 | B5: 2026-08-04 | C5: 103 | D5: Monitor | E5: 2 | F5: 12000 | G5: Online | H5: 24000 | I5: 1500 | J5: 22500
A6: 1005 | B6: 2026-08-05 | C6: 109 | D6: Laptop | E6: 2 | F6: 65000 | G6: Card | H6: 130000 | I6: 10000 | J6: 120000
A7: 1006 | B7: 2026-08-06 | C7: 101 | D7: Keyboard | E7: 4 | F7: 1500 | G7: UPI | H7: 6000 | I7: 300 | J7: 5700
A8: 1007 | B8: 2026-08-07 | C8: 104 | D8: Monitor | E8: 1 | F8: 12000 | G8: Online | H8: 12000 | I8: 500 | J8: 11500
A9: 1008 | B9: 2026-08-08 | C9: 105 | D9: Mouse | E9: 10 | F9: 800 | G9: UPI | H9: 8000 | I9: 400 | J9: 7600
A10: 1009 | B10: 2026-08-09 | C10: 103 | D10: Laptop | E10: 1 | F10: 65000 | G10: Card | H10: 65000 | I10: 5000 | J10: 60000
A11: 1010 | B11: 2026-08-10 | C11: 109 | D11: Monitor | E11: 3 | F11: 12000 | G11: Online | H11: 36000 | I11: 2000 | J11: 34000
A12: 1011 | B12: 2026-08-11 | C12: 107 | D12: Keyboard | E12: 6 | F12: 1500 | G12: UPI | H12: 9000 | I12: 450 | J12: 8550
A13: 1012 | B13: 2026-08-12 | C13: 108 | D13: Mouse | E13: 8 | F13: 800 | G13: Card | H13: 6400 | I13: 300 | J13: 6100

Sheet Employees
A1: Employee_ID | B1: Employee_Name | C1: Department | D1: Salary | E1: City
A2: 101 | B2: Aarav Sharma | C2: IT | D2: 55000 | E2: Delhi
A3: 102 | B3: Diya Gupta | C3: HR | D3: 42000 | E3: Meerut
A4: 103 | B4: Rohan Verma | C4: IT | D4: 68000 | E4: Noida
A5: 104 | B5: Ananya Singh | C5: Sales | D5: 48000 | E5: Delhi
A6: 105 | B6: Kabir Jain | C6: Sales | D6: 62000 | E6: Ghaziabad
A7: 106 | B7: Meera Kapoor | C7: Finance | D7: 72000 | E7: Noida
A8: 107 | B8: Arjun Mehta | C8: IT | D8: 59000 | E8: Meerut
A9: 108 | B9: Isha Malhotra | C9: Finance | D9: 65000 | E9: Delhi
A10: 109 | B10: Vivaan Bansal | C10: Sales | D10: 53000 | E10: Noida
A11: 110 | B11: Sara Khan | C11: HR | D11: 45000 | E11: Meerut

Sheet Functions
A1: Employee_ID | B1: Employee_Name | C1: Department | D1: Salary | E1: Salary_Status | F1: IT_Count | G1: IT_Total_Salary | I1: Function | J1: Example | K1: Purpose
A2: =Employees!A2 | B2: =Employees!B2 | C2: =Employees!C2 | D2: =Employees!D2 | E2: =IF(D2>=60000,"High","Normal") | F2: =COUNTIF(Employees!C$2:C$11,C2) | G2: =SUMIF(Employees!C$2:C$11,C2,Employees!D$2:D$11) | I2: IF() | J2: =IF(D2>=60000,"High","Normal") | K2: Returns one result when a condition is true and another when false.
A3: =Employees!A3 | B3: =Employees!B3 | C3: =Employees!C3 | D3: =Employees!D3 | E3: =IF(D3>=60000,"High","Normal") | F3: =COUNTIF(Employees!C$2:C$11,C3) | G3: =SUMIF(Employees!C$2:C$11,C3,Employees!D$2:D$11) | I3: COUNTIF() | J3: =COUNTIF(Employees!C$2:C$11,"IT") | K3: Counts cells meeting a condition.
A4: =Employees!A4 | B4: =Employees!B4 | C4: =Employees!C4 | D4: =Employees!D4 | E4: =IF(D4>=60000,"High","Normal") | F4: =COUNTIF(Employees!C$2:C$11,C4) | G4: =SUMIF(Employees!C$2:C$11,C4,Employees!D$2:D$11) | I4: SUMIF() | J4: =SUMIF(Employees!C$2:C$11,"IT",Employees!D$2:D$11) | K4: Adds values that meet a condition.
A5: =Employees!A5 | B5: =Employees!B5 | C5: =Employees!C5 | D5: =Employees!D5 | E5: =IF(D5>=60000,"High","Normal") | F5: =COUNTIF(Employees!C$2:C$11,C5) | G5: =SUMIF(Employees!C$2:C$11,C5,Employees!D$2:D$11)
A6: =Employees!A6 | B6: =Employees!B6 | C6: =Employees!C6 | D6: =Employees!D6 | E6: =IF(D6>=60000,"High","Normal") | F6: =COUNTIF(Employees!C$2:C$11,C6) | G6: =SUMIF(Employees!C$2:C$11,C6,Employees!D$2:D$11)
A7: =Employees!A7 | B7: =Employees!B7 | C7: =Employees!C7 | D7: =Employees!D7 | E7: =IF(D7>=60000,"High","Normal") | F7: =COUNTIF(Employees!C$2:C$11,C7) | G7: =SUMIF(Employees!C$2:C$11,C7,Employees!D$2:D$11)
A8: =Employees!A8 | B8: =Employees!B8 | C8: =Employees!C8 | D8: =Employees!D8 | E8: =IF(D8>=60000,"High","Normal") | F8: =COUNTIF(Employees!C$2:C$11,C8) | G8: =SUMIF(Employees!C$2:C$11,C8,Employees!D$2:D$11)
A9: =Employees!A9 | B9: =Employees!B9 | C9: =Employees!C9 | D9: =Employees!D9 | E9: =IF(D9>=60000,"High","Normal") | F9: =COUNTIF(Employees!C$2:C$11,C9) | G9: =SUMIF(Employees!C$2:C$11,C9,Employees!D$2:D$11)
A10: =Employees!A10 | B10: =Employees!B10 | C10: =Employees!C10 | D10: =Employees!D10 | E10: =IF(D10>=60000,"High","Normal") | F10: =COUNTIF(Employees!C$2:C$11,C10) | G10: =SUMIF(Employees!C$2:C$11,C10,Employees!D$2:D$11)
A11: =Employees!A11 | B11: =Employees!B11 | C11: =Employees!C11 | D11: =Employees!D11 | E11: =IF(D11>=60000,"High","Normal") | F11: =COUNTIF(Employees!C$2:C$11,C11) | G11: =SUMIF(Employees!C$2:C$11,C11,Employees!D$2:D$11)

Sheet LookupDemo
A1: Employee_ID | B1: Employee_Name | C1: Department | D1: Salary | E1: VLOOKUP_Salary | F1: XLOOKUP_Department
A2: 101 | B2: =VLOOKUP(A2,Employees!A:E,2,FALSE) | C2: =VLOOKUP(A2,Employees!A:E,3,FALSE) | D2: =VLOOKUP(A2,Employees!A:E,4,FALSE) | E2: =VLOOKUP(A2,Employees!A:E,4,FALSE) | F2: =XLOOKUP(A2,Employees!A:A,Employees!C:C,"Not Found")
A3: 103 | B3: =VLOOKUP(A3,Employees!A:E,2,FALSE) | C3: =VLOOKUP(A3,Employees!A:E,3,FALSE) | D3: =VLOOKUP(A3,Employees!A:E,4,FALSE) | E3: =VLOOKUP(A3,Employees!A:E,4,FALSE) | F3: =XLOOKUP(A3,Employees!A:A,Employees!C:C,"Not Found")
A4: 105 | B4: =VLOOKUP(A4,Employees!A:E,2,FALSE) | C4: =VLOOKUP(A4,Employees!A:E,3,FALSE) | D4: =VLOOKUP(A4,Employees!A:E,4,FALSE) | E4: =VLOOKUP(A4,Employees!A:E,4,FALSE) | F4: =XLOOKUP(A4,Employees!A:A,Employees!C:C,"Not Found")
A5: 108 | B5: =VLOOKUP(A5,Employees!A:E,2,FALSE) | C5: =VLOOKUP(A5,Employees!A:E,3,FALSE) | D5: =VLOOKUP(A5,Employees!A:E,4,FALSE) | E5: =VLOOKUP(A5,Employees!A:E,4,FALSE) | F5: =XLOOKUP(A5,Employees!A:A,Employees!C:C,"Not Found")

Sheet PivotSummary
A1: Department | B1: Employees | C1: Total Salary | D1: Average Salary | F1: Chart: Total Salary by Department
A2: IT | B2: =COUNTIF(Employees!C:C,A2) | C2: =SUMIF(Employees!C:C,A2,Employees!D:D) | D2: =AVERAGEIF(Employees!C:C,A2,Employees!D:D)
A3: HR | B3: =COUNTIF(Employees!C:C,A3) | C3: =SUMIF(Employees!C:C,A3,Employees!D:D) | D3: =AVERAGEIF(Employees!C:C,A3,Employees!D:D)
A4: Sales | B4: =COUNTIF(Employees!C:C,A4) | C4: =SUMIF(Employees!C:C,A4,Employees!D:D) | D4: =AVERAGEIF(Employees!C:C,A4,Employees!D:D)
A5: Finance | B5: =COUNTIF(Employees!C:C,A5) | C5: =SUMIF(Employees!C:C,A5,Employees!D:D) | D5: =AVERAGEIF(Employees!C:C,A5,Employees!D:D)

Sheet ReadMe
A1: Assignment | B1: SQL & Excel Data Analytics Assignment
A2: Dataset | B2: Sales and Employee sample dataset created for practice.
A3: SQL Dialect | B3: MySQL 8.0 syntax; RIGHT JOIN is included as required.
A4: Excel Tasks | B4: Formatting, sorting/filtering, conditional formatting, IF/COUNTIF/SUMIF, VLOOKUP/XLOOKUP, pivot-style summary and chart.
A5: Important | B5: Open the workbook in Microsoft Excel so formulas such as XLOOKUP calculate correctly.
