Workbook

Sheet Read_Me
A1: SQL & Excel Data Analytics Assignment
A2: Task 6 | B2: Sales_Data: formatting, sorting and filtering
A3: Task 7 | B3: Excel_Functions: IF, COUNTIF, SUMIF and conditional formatting
A4: Task 8 | B4: Lookup: VLOOKUP and XLOOKUP
A5: Task 9 | B5: Pivot_Summary: category summary and chart

Sheet Sales_Data
A1: Sale_ID | B1: Sale_Date | C1: Employee_ID | D1: Product_ID | E1: Quantity | F1: Total_Sales | G1: Payment_Method
A2: 1001 | B2: 2026-01-05 | C2: 101 | D2: 201 | E2: 2 | F2: 130000 | G2: Online
A3: 1002 | B3: 2026-01-08 | C3: 102 | D3: 202 | E3: 10 | F3: 8000 | G3: UPI
A4: 1003 | B4: 2026-01-15 | C4: 107 | D4: 203 | E4: 5 | F4: 7500 | G4: Card
A5: 1004 | B5: 2026-02-02 | C5: 103 | D5: 204 | E5: 3 | F5: 54000 | G5: Online
A6: 1005 | B6: 2026-02-10 | C6: 105 | D6: 205 | E6: 8 | F6: 20000 | G6: UPI
A7: 1006 | B7: 2026-02-18 | C7: 106 | D7: 206 | E7: 4 | F7: 48000 | G7: Card
A8: 1007 | B8: 2026-03-03 | C8: 101 | D8: 201 | E8: 1 | F8: 65000 | G8: Card
A9: 1008 | B9: 2026-03-12 | C9: 107 | D9: 204 | E9: 2 | F9: 36000 | G9: UPI
A10: 1009 | B10: 2026-03-20 | C10: 102 | D10: 205 | E10: 6 | F10: 15000 | G10: Online
A11: 1010 | B11: 2026-04-01 | C11: 105 | D11: 201 | E11: 3 | F11: 195000 | G11: Card

Sheet Employees
A1: Employee_ID | B1: Employee_Name | C1: City | D1: Department | E1: Salary
A2: 101 | B2: Aarav Sharma | C2: Delhi | D2: Sales | E2: 45000
A3: 102 | B3: Priya Singh | C3: Noida | D3: Sales | E3: 52000
A4: 103 | B4: Rohan Verma | C4: Meerut | D4: IT | E4: 68000
A5: 104 | B5: Ananya Gupta | C5: Delhi | D5: HR | E5: 48000
A6: 105 | B6: Vikram Kumar | C6: Ghaziabad | D6: IT | E6: 72000
A7: 106 | B7: Neha Jain | C7: Noida | D7: Marketing | E7: 55000
A8: 107 | B8: Karan Tyagi | C8: Meerut | D8: Sales | E8: 61000
A9: 108 | B9: Simran Kaur | C9: Delhi | D9: Marketing | E9: 58000

Sheet Products
A1: Product_ID | B1: Product_Name | C1: Category | D1: Price
A2: 201 | B2: Laptop | C2: Electronics | D2: 65000
A3: 202 | B3: Mouse | C3: Accessories | D3: 800
A4: 203 | B4: Keyboard | C4: Accessories | D4: 1500
A5: 204 | B5: Monitor | C5: Electronics | D5: 18000
A6: 205 | B6: Headphones | C6: Accessories | D6: 2500
A7: 206 | B7: Printer | C7: Electronics | D7: 12000

Sheet Excel_Functions
A1: Employee_ID | B1: Employee_Name | C1: Salary | D1: Performance | E1: Bonus_Eligible | G1: COUNTIF | H1: =COUNTIF(D2:D9,"High")
A2: 101 | B2: Aarav Sharma | C2: 45000 | D2: =IF(C2>=55000,"High","Standard") | E2: =IF(C2>=60000,"Yes","No") | G2: SUMIF | H2: =SUMIF(D2:D9,"High",C2:C9)
A3: 102 | B3: Priya Singh | C3: 52000 | D3: =IF(C3>=55000,"High","Standard") | E3: =IF(C3>=60000,"Yes","No") | G3: IF | H3: =IF(C2>=55000,"High","Standard")
A4: 103 | B4: Rohan Verma | C4: 68000 | D4: =IF(C4>=55000,"High","Standard") | E4: =IF(C4>=60000,"Yes","No")
A5: 104 | B5: Ananya Gupta | C5: 48000 | D5: =IF(C5>=55000,"High","Standard") | E5: =IF(C5>=60000,"Yes","No")
A6: 105 | B6: Vikram Kumar | C6: 72000 | D6: =IF(C6>=55000,"High","Standard") | E6: =IF(C6>=60000,"Yes","No")
A7: 106 | B7: Neha Jain | C7: 55000 | D7: =IF(C7>=55000,"High","Standard") | E7: =IF(C7>=60000,"Yes","No")
A8: 107 | B8: Karan Tyagi | C8: 61000 | D8: =IF(C8>=55000,"High","Standard") | E8: =IF(C8>=60000,"Yes","No")
A9: 108 | B9: Simran Kaur | C9: 58000 | D9: =IF(C9>=55000,"High","Standard") | E9: =IF(C9>=60000,"Yes","No")

Sheet Lookup
A1: Product_ID | B1: VLOOKUP_Product | C1: VLOOKUP_Price | D1: XLOOKUP_Product | E1: XLOOKUP_Price
A2: 201 | B2: =VLOOKUP(A2,Products!A:D,2,FALSE) | C2: =VLOOKUP(A2,Products!A:D,4,FALSE) | D2: =XLOOKUP(A2,Products!A:A,Products!B:B,"Not Found") | E2: =XLOOKUP(A2,Products!A:A,Products!D:D,"Not Found")
A3: 202 | B3: =VLOOKUP(A3,Products!A:D,2,FALSE) | C3: =VLOOKUP(A3,Products!A:D,4,FALSE) | D3: =XLOOKUP(A3,Products!A:A,Products!B:B,"Not Found") | E3: =XLOOKUP(A3,Products!A:A,Products!D:D,"Not Found")
A4: 203 | B4: =VLOOKUP(A4,Products!A:D,2,FALSE) | C4: =VLOOKUP(A4,Products!A:D,4,FALSE) | D4: =XLOOKUP(A4,Products!A:A,Products!B:B,"Not Found") | E4: =XLOOKUP(A4,Products!A:A,Products!D:D,"Not Found")
A5: 204 | B5: =VLOOKUP(A5,Products!A:D,2,FALSE) | C5: =VLOOKUP(A5,Products!A:D,4,FALSE) | D5: =XLOOKUP(A5,Products!A:A,Products!B:B,"Not Found") | E5: =XLOOKUP(A5,Products!A:A,Products!D:D,"Not Found")
A6: 205 | B6: =VLOOKUP(A6,Products!A:D,2,FALSE) | C6: =VLOOKUP(A6,Products!A:D,4,FALSE) | D6: =XLOOKUP(A6,Products!A:A,Products!B:B,"Not Found") | E6: =XLOOKUP(A6,Products!A:A,Products!D:D,"Not Found")
A7: 206 | B7: =VLOOKUP(A7,Products!A:D,2,FALSE) | C7: =VLOOKUP(A7,Products!A:D,4,FALSE) | D7: =XLOOKUP(A7,Products!A:A,Products!B:B,"Not Found") | E7: =XLOOKUP(A7,Products!A:A,Products!D:D,"Not Found")

Sheet Pivot_Summary
A1: Category | B1: Total Sales | C1: Units Sold
A2: Accessories | B2: 50500 | C2: 29
A3: Electronics | B3: 528000 | C3: 15
